lite_tools/__init__.py
lite_tools/commands/__init__.py
lite_tools/commands/cmdline.py
lite_tools/commands/dictionary/__init__.py
lite_tools/commands/dictionary/dict_cmd.py
lite_tools/commands/flush/__init__.py
lite_tools/commands/flush/flush_cmd.py
lite_tools/commands/fresh/__init__.py
lite_tools/commands/fresh/dictionary.py
lite_tools/commands/fresh/fresh_cmd.py
lite_tools/commands/fresh/useragent.py
lite_tools/commands/news/__init__.py
lite_tools/commands/news/get_blog_rank.py
lite_tools/commands/news/get_global_news.py
lite_tools/commands/news/news_cmd.py
lite_tools/commands/news/script_hot_news.py
lite_tools/commands/news/z_sfg.py
lite_tools/commands/today/__init__.py
lite_tools/commands/today/fisher_date.py
lite_tools/commands/today/oil_price.py
lite_tools/commands/today/script_almanac.py
lite_tools/commands/today/today_utils.py
lite_tools/commands/trans/__init__.py
lite_tools/commands/trans/excel.py
lite_tools/commands/trans/pdf.py
lite_tools/commands/trans/pic.py
lite_tools/commands/trans/word.py
lite_tools/commands/weather/__init__.py
lite_tools/commands/weather/weather_cmd.py
lite_tools/commands/weather/weather_main.py
lite_tools/commands/whsecret/__init__.py
lite_tools/commands/whsecret/bearsay.py
lite_tools/commands/whsecret/morse.py
lite_tools/commands/whsecret/says.py
lite_tools/exceptions/AnimeExceptions.py
lite_tools/exceptions/CacheExceptions.py
lite_tools/exceptions/DictExceptions.py
lite_tools/exceptions/SqlExceptions.py
lite_tools/exceptions/StringExceptions.py
lite_tools/exceptions/TimeExceptions.py
lite_tools/exceptions/__init__.py
lite_tools/logs/__init__.py
lite_tools/logs/sql.py
lite_tools/tools/__init__.py
lite_tools/tools/core/__init__.py
lite_tools/tools/core/ip_info.py
lite_tools/tools/core/lib_base64.py
lite_tools/tools/core/lib_hashlib.py
lite_tools/tools/core/lite_cache.py
lite_tools/tools/core/lite_file.py
lite_tools/tools/core/lite_ja3.py
lite_tools/tools/core/lite_match.py
lite_tools/tools/core/lite_parser.py
lite_tools-0.4.13.4.dist-info/licenses/LICENSE
lite_tools-0.4.13.4.dist-info/METADATA
lite_tools-0.4.13.4.dist-info/WHEEL
lite_tools-0.4.13.4.dist-info/entry_points.txt
lite_tools-0.4.13.4.dist-info/top_level.txt
lite_tools-0.4.13.4.dist-info/RECORD
