Metadata-Version: 2.4
Name: lite-tools
Version: 0.4.13.4
Summary: 一些让你效率提升的小工具集合包[还在持续增加及优化]
Author-email: Empty <lodgeheartfilia@163.com>
License: MIT License
Project-URL: homepage, https://github.com/Heartfilia/lite_tools
Classifier: Intended Audience :: Developers
Classifier: Operating System :: OS Independent
Classifier: Natural Language :: Chinese (Simplified)
Classifier: Programming Language :: Python :: 3
Requires-Python: >=3.8
License-File: LICENSE
Requires-Dist: loguru
Requires-Dist: telnetlib3
Requires-Dist: prettytable
Requires-Dist: datetime
Requires-Dist: urllib3
Requires-Dist: requests
Requires-Dist: redis[hiredis]>=4.5.0
Provides-Extra: net
Requires-Dist: pymysql; extra == "net"
Requires-Dist: pyyaml; extra == "net"
Requires-Dist: usepy; extra == "net"
Requires-Dist: lxml; extra == "net"
Requires-Dist: dbutils; extra == "net"
Requires-Dist: aiomysql; extra == "net"
Provides-Extra: all
Requires-Dist: colorama; extra == "all"
Requires-Dist: pydantic; extra == "all"
Requires-Dist: reportlab; extra == "all"
Requires-Dist: Pillow; extra == "all"
Requires-Dist: pymysql; extra == "all"
Requires-Dist: pyyaml; extra == "all"
Requires-Dist: requests; extra == "all"
Requires-Dist: urllib3; extra == "all"
Requires-Dist: usepy; extra == "all"
Requires-Dist: lxml; extra == "all"
Requires-Dist: dbutils; extra == "all"
Requires-Dist: aiomysql; extra == "all"
Requires-Dist: python-multipart; extra == "all"
Dynamic: license-file
